hsc_instructions/__init__.py
hsc_instructions/arg_types.py
hsc_instructions/errors.py
hsc_instructions/instruction.py
hsc_instructions/instruction_info.py
hsc_instructions/parsable.py
hsc_instructions/sized_numbers.py
hsc_instructions/utilities.py
hsc_instructions-0.5.1.dist-info/WHEEL
hsc_instructions-0.5.1.dist-info/METADATA
hsc_instructions-0.5.1.dist-info/RECORD
